Workbook

Sheet Todos os Gastos
A1: Data | B1: Descrição | C1: Valor | D1: Pago | E1: Lote usado
A2: 46062 | B2: Cartão Azul | C2: 2063.23 | D2: OK | E2: Lote 2063,11 fev.
A3: 46062 | B3: Cartão Azul | C3: 6014.05 | D3: OK | E3: Lote 10342 fev.
A4: 46063 | B4: Cartão PS | C4: 123.44 | D4: OK | E4: Lote 4000 fev.
A5: 46064 | B5: Cemig | C5: 95.12 | D5: OK | E5: Lote 4124,75 fev.
A6: 46064 | B6: Pelada | C6: 50 | D6: OK | E6: Lote 4124,75 fev.
A7: 46065 | B7: Aluguel | C7: 981.95 | D7: OK | E7: Lote 10342 fev.
A8: 46065 | B8: IPVA | C8: 1407.65 | D8: OK | E8: Lote 10342 fev.
A9: 46069 | B9: Internet | C9: 132.4 | D9: OK | E9: Lote 10342 fev.
A10: 46072 | B10: Escola | C10: 2831.4 | D10: OK | E10: Lote 4124,75 fev.
A11: 46072 | B11: Material | C11: 460 | D11: OK | E11: Lote 10342 fev.
A12: 46073 | B12: Condomínio | C12: 74.18 | D12: OK | E12: Lote 4000 fev.
A13: 46083 | B13: Cartão NU | C13: 1771.95 | D13: OK | E13: Lote 4000 fev.
... A60: 46126 | B60: Escola | C60: 2472.89 | D60: OK | E60: Lote 3600 abr.
A61: 46127 | B61: Internet | C61: 132.4
A62: 46132 | B62: Cartão Azul | C62: 6350.01
A63: 46132 | B63: Cemig | C63: 98.98
A64: 46132 | B64: Condomínio | C64: 113.31
A65: 46141 | B65: Tratamento Lara | C65: 530
A66: 46146 | B66: Cartão NU | C66: 1500
A67: 46148 | B67: Cemig SIM | C67: 195
A68: 46148 | B68: Faxina Rosa | C68: 950
A69: 46150 | B69: Claro | C69: 120
A70: 46152 | B70: Ginástica Biola | C70: 65
A71: 46153 | B71: Cemig | C71: 95.05
A72: 46154 | B72: Aluguel | C72: 981.95
... A213: 46477 | B213: Licenciamento | C213: 35.62

Sheet Inventário de Lotes
A1: Lote (ID) | B1: Data Aplicação | C1: Valor Original | D1: Investimento
A2: Lote 4000 fev. | B2: 46057 | C2: 4000 | D2: CDB Turbinado
A3: Lote 6630,64 fev. | B3: 46057 | C3: 6630.64 | D3: CDB Turbinado
A4: Lote 10342 fev. | B4: 46058 | C4: 10342 | D4: CDB Turbinado
A5: Lote 4124,75 fev. | B5: 46058 | C5: 4124.75 | D5: CDB Turbinado
A6: Lote 5400 fev. | B6: 46058 | C6: 5400 | D6: CDB Turbinado
A7: Lote 2063,11 fev. | B7: 46059 | C7: 2063.11 | D7: CDB Turbinado
A8: Lote 3000 mar. V | B8: 46084 | C8: 3000 | D8: CDB XP 230%
A9: Lote 3000 mar. B | B9: 46085 | C9: 3000 | D9: CDB XP 230%
A10: Lote 1000 mar. | B10: 46086 | C10: 1003.38 | D10: -
A11: Lote 8500 mar. | B11: 46087 | C11: 8587 | D11: CDB Sofisa 105%
A12: Lote 900 mar. | B12: 46087 | C12: 936.15 | D12: -
A13: Lote 35 abr. | B13: 46113 | C13: 36.02 | D13: -
... A15: Lote 3600 abr. | B15: 46118 | C15: 3589.11 | D15: -
A16: Lote 5680 abr. | B16: 46118 | C16: 5680
A17: Lote 7000 mai. | B17: 46145 | C17: 7000
A18: Lote 3600 mai. | B18: 46148 | C18: 3600
A19: Lote 5680 mai. | B19: 46148 | C19: 5680
A20: Lote 7000 jun. | B20: 46175 | C20: 7000
A21: Lote 1800 jun. | B21: 46178 | C21: 1800
A22: Lote 5680 jun. | B22: 46178 | C22: 5680
A23: Lote 7000 jul. | B23: 46205 | C23: 7000
A24: Lote 5680 jul. | B24: 46208 | C24: 5680
A25: Lote 7000 ago. | B25: 46235 | C25: 7000
A26: Lote 5680 ago. | B26: 46238 | C26: 5680
A27: Lote 7000 set. | B27: 46266 | C27: 7000
... A40: Lote 5680 mar. | B40: 46452 | C40: 5680

Sheet Resumo Mensal
A1: Resumo mensal automático | M1: Último mês com dados
J2: Painel executivo mensal | M2: =EOMONTH(MAX(MAX('Todos os Gastos'!$A:$A),MAX('Inventário de Lotes'!$B:$B)),-1)+1 -> 46447
A3: Mês | B3: Gastos totais | C3: Recebidos totais | D3: Saldo mensal | E3: Qtd. gastos | F3: Qtd. recebimentos | G3: Saldo acumulado | J3: Total de gastos | K3: =SUM(B4:B123) -> 210173.87 | M3: Primeiro mês
A4: 46054 | B4: =IF($A4="","",SUMIFS('Todos os Gastos'!$C:$C,'Todos os Gastos'!$A:$A,">="&$A4,'Todos os Gastos'!$A:$A,"<"&EDATE($A4,1))) -> 14233.42 | C4: =IF($A4="","",SUMIFS('Inventário de Lotes'!$C:$C,'Inventário de Lotes'!$B:$B,">="&$A4,'Inventário de Lotes'!$B:$B,"<"&EDATE($A4,1))) -> 32560.5 | D4: =IF($A4="","",C4-B4) -> 18327.08 | E4: =IF($A4="","",COUNTIFS('Todos os Gastos'!$A:$A,">="&$A4,'Todos os Gastos'!$A:$A,"<"&EDATE($A4,1))) -> 11 | F4: =IF($A4="","",COUNTIFS('Inventário de Lotes'!$B:$B,">="&$A4,'Inventário de Lotes'!$B:$B,"<"&EDATE($A4,1))) -> 6 | G4: =IF($A4="","",SUM($D$4:D4)) -> 18327.08 | J4: Total recebido | K4: =SUM(C4:C123) -> 211129.41 | M4: 46054
A5: =IF(A4<$M$2,EDATE(A4,1),"") -> 46082 | B5: =IF($A5="","",SUMIFS('Todos os Gastos'!$C:$C,'Todos os Gastos'!$A:$A,">="&$A5,'Todos os Gastos'!$A:$A,"<"&EDATE($A5,1))) -> 17340.15 | C5: =IF($A5="","",SUMIFS('Inventário de Lotes'!$C:$C,'Inventário de Lotes'!$B:$B,">="&$A5,'Inventário de Lotes'!$B:$B,"<"&EDATE($A5,1))) -> 16526.53 | D5: =IF($A5="","",C5-B5) -> -813.62 | E5: =IF($A5="","",COUNTIFS('Todos os Gastos'!$A:$A,">="&$A5,'Todos os Gastos'!$A:$A,"<"&EDATE($A5,1))) -> 28 | F5: =IF($A5="","",COUNTIFS('Inventário de Lotes'!$B:$B,">="&$A5,'Inventário de Lotes'!$B:$B,"<"&EDATE($A5,1))) -> 5 | G5: =IF($A5="","",SUM($D$4:D5)) -> 17513.46 | J5: Saldo acumulado até mês atual | K5: =SUMIFS(D4:D123,A4:A123,"<="&EOMONTH(TODAY(),0)+1-1,A4:A123,"<>") -> 14857.1
A6: =IF(A5<$M$2,EDATE(A5,1),"") -> 46113 | B6: =IF($A6="","",SUMIFS('Todos os Gastos'!$C:$C,'Todos os Gastos'!$A:$A,">="&$A6,'Todos os Gastos'!$A:$A,"<"&EDATE($A6,1))) -> 19818.74 | C6: =IF($A6="","",SUMIFS('Inventário de Lotes'!$C:$C,'Inventário de Lotes'!$B:$B,">="&$A6,'Inventário de Lotes'!$B:$B,"<"&EDATE($A6,1))) -> 17162.38 | D6: =IF($A6="","",C6-B6) -> -2656.36 | E6: =IF($A6="","",COUNTIFS('Todos os Gastos'!$A:$A,">="&$A6,'Todos os Gastos'!$A:$A,"<"&EDATE($A6,1))) -> 25 | F6: =IF($A6="","",COUNTIFS('Inventário de Lotes'!$B:$B,">="&$A6,'Inventário de Lotes'!$B:$B,"<"&EDATE($A6,1))) -> 4 | G6: =IF($A6="","",SUM($D$4:D6)) -> 14857.1 | J6: Saldo acumulado final | K6: =G17 -> 955.54
A7: =IF(A6<$M$2,EDATE(A6,1),"") -> 46143 | B7: =IF($A7="","",SUMIFS('Todos os Gastos'!$C:$C,'Todos os Gastos'!$A:$A,">="&$A7,'Todos os Gastos'!$A:$A,"<"&EDATE($A7,1))) -> 14234.11 | C7: =IF($A7="","",SUMIFS('Inventário de Lotes'!$C:$C,'Inventário de Lotes'!$B:$B,">="&$A7,'Inventário de Lotes'!$B:$B,"<"&EDATE($A7,1))) -> 16280 | D7: =IF($A7="","",C7-B7) -> 2045.89 | E7: =IF($A7="","",COUNTIFS('Todos os Gastos'!$A:$A,">="&$A7,'Todos os Gastos'!$A:$A,"<"&EDATE($A7,1))) -> 12 | F7: =IF($A7="","",COUNTIFS('Inventário de Lotes'!$B:$B,">="&$A7,'Inventário de Lotes'!$B:$B,"<"&EDATE($A7,1))) -> 3 | G7: =IF($A7="","",SUM($D$4:D7)) -> 16902.99 | J7: Saldo do mês atual | K7: =SUMIFS(D4:D123,A4:A123,">="&EOMONTH(TODAY(),-1)+1,A4:A123,"<"&EDATE(EOMONTH(TODAY(),-1)+1,1)) -> -2656.36
A8: =IF(A7<$M$2,EDATE(A7,1),"") -> 46174 | B8: =IF($A8="","",SUMIFS('Todos os Gastos'!$C:$C,'Todos os Gastos'!$A:$A,">="&$A8,'Todos os Gastos'!$A:$A,"<"&EDATE($A8,1))) -> 13844.18 | C8: =IF($A8="","",SUMIFS('Inventário de Lotes'!$C:$C,'Inventário de Lotes'!$B:$B,">="&$A8,'Inventário de Lotes'!$B:$B,"<"&EDATE($A8,1))) -> 14480 | D8: =IF($A8="","",C8-B8) -> 635.82 | E8: =IF($A8="","",COUNTIFS('Todos os Gastos'!$A:$A,">="&$A8,'Todos os Gastos'!$A:$A,"<"&EDATE($A8,1))) -> 13 | F8: =IF($A8="","",COUNTIFS('Inventário de Lotes'!$B:$B,">="&$A8,'Inventário de Lotes'!$B:$B,"<"&EDATE($A8,1))) -> 3 | G8: =IF($A8="","",SUM($D$4:D8)) -> 17538.81 | J8: Média mensal do saldo | K8: =AVERAGEIF(D4:D123,"<>",D4:D123) -> 68.252857
A9: =IF(A8<$M$2,EDATE(A8,1),"") -> 46204 | B9: =IF($A9="","",SUMIFS('Todos os Gastos'!$C:$C,'Todos os Gastos'!$A:$A,">="&$A9,'Todos os Gastos'!$A:$A,"<"&EDATE($A9,1))) -> 13264.18 | C9: =IF($A9="","",SUMIFS('Inventário de Lotes'!$C:$C,'Inventário de Lotes'!$B:$B,">="&$A9,'Inventário de Lotes'!$B:$B,"<"&EDATE($A9,1))) -> 12680 | D9: =IF($A9="","",C9-B9) -> -584.18 | E9: =IF($A9="","",COUNTIFS('Todos os Gastos'!$A:$A,">="&$A9,'Todos os Gastos'!$A:$A,"<"&EDATE($A9,1))) -> 12 | F9: =IF($A9="","",COUNTIFS('Inventário de Lotes'!$B:$B,">="&$A9,'Inventário de Lotes'!$B:$B,"<"&EDATE($A9,1))) -> 2 | G9: =IF($A9="","",SUM($D$4:D9)) -> 16954.63 | J9: Maior gasto mensal | K9: =MAX(B4:B123) -> 19818.74
A10: =IF(A9<$M$2,EDATE(A9,1),"") -> 46235 | B10: =IF($A10="","",SUMIFS('Todos os Gastos'!$C:$C,'Todos os Gastos'!$A:$A,">="&$A10,'Todos os Gastos'!$A:$A,"<"&EDATE($A10,1))) -> 13824.18 | C10: =IF($A10="","",SUMIFS('Inventário de Lotes'!$C:$C,'Inventário de Lotes'!$B:$B,">="&$A10,'Inventário de Lotes'!$B:$B,"<"&EDATE($A10,1))) -> 12680 | D10: =IF($A10="","",C10-B10) -> -1144.18 | E10: =IF($A10="","",COUNTIFS('Todos os Gastos'!$A:$A,">="&$A10,'Todos os Gastos'!$A:$A,"<"&EDATE($A10,1))) -> 14 | F10: =IF($A10="","",COUNTIFS('Inventário de Lotes'!$B:$B,">="&$A10,'Inventário de Lotes'!$B:$B,"<"&EDATE($A10,1))) -> 2 | G10: =IF($A10="","",SUM($D$4:D10)) -> 15810.45 | J10: Maior recebido mensal | K10: =MAX(C4:C123) -> 32560.5
A11: =IF(A10<$M$2,EDATE(A10,1),"") -> 46266 | B11: =IF($A11="","",SUMIFS('Todos os Gastos'!$C:$C,'Todos os Gastos'!$A:$A,">="&$A11,'Todos os Gastos'!$A:$A,"<"&EDATE($A11,1))) -> 14474.18 | C11: =IF($A11="","",SUMIFS('Inventário de Lotes'!$C:$C,'Inventário de Lotes'!$B:$B,">="&$A11,'Inventário de Lotes'!$B:$B,"<"&EDATE($A11,1))) -> 12680 | D11: =IF($A11="","",C11-B11) -> -1794.18 | E11: =IF($A11="","",COUNTIFS('Todos os Gastos'!$A:$A,">="&$A11,'Todos os Gastos'!$A:$A,"<"&EDATE($A11,1))) -> 13 | F11: =IF($A11="","",COUNTIFS('Inventário de Lotes'!$B:$B,">="&$A11,'Inventário de Lotes'!$B:$B,"<"&EDATE($A11,1))) -> 2 | G11: =IF($A11="","",SUM($D$4:D11)) -> 14016.27 | J11: Período coberto | K11: =TEXT(A4,"mmm/yy")&" a "&TEXT($M$2,"mmm/yy") -> fev./26 a mar./27
A12: =IF(A11<$M$2,EDATE(A11,1),"") -> 46296 | B12: =IF($A12="","",SUMIFS('Todos os Gastos'!$C:$C,'Todos os Gastos'!$A:$A,">="&$A12,'Todos os Gastos'!$A:$A,"<"&EDATE($A12,1))) -> 14073.98 | C12: =IF($A12="","",SUMIFS('Inventário de Lotes'!$C:$C,'Inventário de Lotes'!$B:$B,">="&$A12,'Inventário de Lotes'!$B:$B,"<"&EDATE($A12,1))) -> 12680 | D12: =IF($A12="","",C12-B12) -> -1393.98 | E12: =IF($A12="","",COUNTIFS('Todos os Gastos'!$A:$A,">="&$A12,'Todos os Gastos'!$A:$A,"<"&EDATE($A12,1))) -> 15 | F12: =IF($A12="","",COUNTIFS('Inventário de Lotes'!$B:$B,">="&$A12,'Inventário de Lotes'!$B:$B,"<"&EDATE($A12,1))) -> 2 | G12: =IF($A12="","",SUM($D$4:D12)) -> 12622.29 | J12: Mês atual | K12: =TEXT(TODAY(),"mmm/yy") -> abr./26
A13: =IF(A12<$M$2,EDATE(A12,1),"") -> 46327 | B13: =IF($A13="","",SUMIFS('Todos os Gastos'!$C:$C,'Todos os Gastos'!$A:$A,">="&$A13,'Todos os Gastos'!$A:$A,"<"&EDATE($A13,1))) -> 13574.18 | C13: =IF($A13="","",SUMIFS('Inventário de Lotes'!$C:$C,'Inventário de Lotes'!$B:$B,">="&$A13,'Inventário de Lotes'!$B:$B,"<"&EDATE($A13,1))) -> 12680 | D13: =IF($A13="","",C13-B13) -> -894.18 | E13: =IF($A13="","",COUNTIFS('Todos os Gastos'!$A:$A,">="&$A13,'Todos os Gastos'!$A:$A,"<"&EDATE($A13,1))) -> 13 | F13: =IF($A13="","",COUNTIFS('Inventário de Lotes'!$B:$B,">="&$A13,'Inventário de Lotes'!$B:$B,"<"&EDATE($A13,1))) -> 2 | G13: =IF($A13="","",SUM($D$4:D13)) -> 11728.11
A14: =IF(A13<$M$2,EDATE(A13,1),"") -> 46357 | B14: =IF($A14="","",SUMIFS('Todos os Gastos'!$C:$C,'Todos os Gastos'!$A:$A,">="&$A14,'Todos os Gastos'!$A:$A,"<"&EDATE($A14,1))) -> 17094.18 | C14: =IF($A14="","",SUMIFS('Inventário de Lotes'!$C:$C,'Inventário de Lotes'!$B:$B,">="&$A14,'Inventário de Lotes'!$B:$B,"<"&EDATE($A14,1))) -> 12680 | D14: =IF($A14="","",C14-B14) -> -4414.18 | E14: =IF($A14="","",COUNTIFS('Todos os Gastos'!$A:$A,">="&$A14,'Todos os Gastos'!$A:$A,"<"&EDATE($A14,1))) -> 14 | F14: =IF($A14="","",COUNTIFS('Inventário de Lotes'!$B:$B,">="&$A14,'Inventário de Lotes'!$B:$B,"<"&EDATE($A14,1))) -> 2 | G14: =IF($A14="","",SUM($D$4:D14)) -> 7313.93
A15: =IF(A14<$M$2,EDATE(A14,1),"") -> 46388 | B15: =IF($A15="","",SUMIFS('Todos os Gastos'!$C:$C,'Todos os Gastos'!$A:$A,">="&$A15,'Todos os Gastos'!$A:$A,"<"&EDATE($A15,1))) -> 12588.85 | C15: =IF($A15="","",SUMIFS('Inventário de Lotes'!$C:$C,'Inventário de Lotes'!$B:$B,">="&$A15,'Inventário de Lotes'!$B:$B,"<"&EDATE($A15,1))) -> 12680 | D15: =IF($A15="","",C15-B15) -> 91.15 | E15: =IF($A15="","",COUNTIFS('Todos os Gastos'!$A:$A,">="&$A15,'Todos os Gastos'!$A:$A,"<"&EDATE($A15,1))) -> 11 | F15: =IF($A15="","",COUNTIFS('Inventário de Lotes'!$B:$B,">="&$A15,'Inventário de Lotes'!$B:$B,"<"&EDATE($A15,1))) -> 2 | G15: =IF($A15="","",SUM($D$4:D15)) -> 7405.08
A16: =IF(A15<$M$2,EDATE(A15,1),"") -> 46419 | B16: =IF($A16="","",SUMIFS('Todos os Gastos'!$C:$C,'Todos os Gastos'!$A:$A,">="&$A16,'Todos os Gastos'!$A:$A,"<"&EDATE($A16,1))) -> 15735.95 | C16: =IF($A16="","",SUMIFS('Inventário de Lotes'!$C:$C,'Inventário de Lotes'!$B:$B,">="&$A16,'Inventário de Lotes'!$B:$B,"<"&EDATE($A16,1))) -> 12680 | D16: =IF($A16="","",C16-B16) -> -3055.95 | E16: =IF($A16="","",COUNTIFS('Todos os Gastos'!$A:$A,">="&$A16,'Todos os Gastos'!$A:$A,"<"&EDATE($A16,1))) -> 15 | F16: =IF($A16="","",COUNTIFS('Inventário de Lotes'!$B:$B,">="&$A16,'Inventário de Lotes'!$B:$B,"<"&EDATE($A16,1))) -> 2 | G16: =IF($A16="","",SUM($D$4:D16)) -> 4349.13
A17: =IF(A16<$M$2,EDATE(A16,1),"") -> 46447 | B17: =IF($A17="","",SUMIFS('Todos os Gastos'!$C:$C,'Todos os Gastos'!$A:$A,">="&$A17,'Todos os Gastos'!$A:$A,"<"&EDATE($A17,1))) -> 16073.59 | C17: =IF($A17="","",SUMIFS('Inventário de Lotes'!$C:$C,'Inventário de Lotes'!$B:$B,">="&$A17,'Inventário de Lotes'!$B:$B,"<"&EDATE($A17,1))) -> 12680 | D17: =IF($A17="","",C17-B17) -> -3393.59 | E17: =IF($A17="","",COUNTIFS('Todos os Gastos'!$A:$A,">="&$A17,'Todos os Gastos'!$A:$A,"<"&EDATE($A17,1))) -> 16 | F17: =IF($A17="","",COUNTIFS('Inventário de Lotes'!$B:$B,">="&$A17,'Inventário de Lotes'!$B:$B,"<"&EDATE($A17,1))) -> 2 | G17: =IF($A17="","",SUM($D$4:D17)) -> 955.54
A18: =IF(A17<$M$2,EDATE(A17,1),"") | B18: =IF($A18="","",SUMIFS('Todos os Gastos'!$C:$C,'Todos os Gastos'!$A:$A,">="&$A18,'Todos os Gastos'!$A:$A,"<"&EDATE($A18,1))) | C18: =IF($A18="","",SUMIFS('Inventário de Lotes'!$C:$C,'Inventário de Lotes'!$B:$B,">="&$A18,'Inventário de Lotes'!$B:$B,"<"&EDATE($A18,1))) | D18: =IF($A18="","",C18-B18) | E18: =IF($A18="","",COUNTIFS('Todos os Gastos'!$A:$A,">="&$A18,'Todos os Gastos'!$A:$A,"<"&EDATE($A18,1))) | F18: =IF($A18="","",COUNTIFS('Inventário de Lotes'!$B:$B,">="&$A18,'Inventário de Lotes'!$B:$B,"<"&EDATE($A18,1))) | G18: =IF($A18="","",SUM($D$4:D18))
A19: =IF(A18<$M$2,EDATE(A18,1),"") | B19: =IF($A19="","",SUMIFS('Todos os Gastos'!$C:$C,'Todos os Gastos'!$A:$A,">="&$A19,'Todos os Gastos'!$A:$A,"<"&EDATE($A19,1))) | C19: =IF($A19="","",SUMIFS('Inventário de Lotes'!$C:$C,'Inventário de Lotes'!$B:$B,">="&$A19,'Inventário de Lotes'!$B:$B,"<"&EDATE($A19,1))) | D19: =IF($A19="","",C19-B19) | E19: =IF($A19="","",COUNTIFS('Todos os Gastos'!$A:$A,">="&$A19,'Todos os Gastos'!$A:$A,"<"&EDATE($A19,1))) | F19: =IF($A19="","",COUNTIFS('Inventário de Lotes'!$B:$B,">="&$A19,'Inventário de Lotes'!$B:$B,"<"&EDATE($A19,1))) | G19: =IF($A19="","",SUM($D$4:D19))
A20: =IF(A19<$M$2,EDATE(A19,1),"") | B20: =IF($A20="","",SUMIFS('Todos os Gastos'!$C:$C,'Todos os Gastos'!$A:$A,">="&$A20,'Todos os Gastos'!$A:$A,"<"&EDATE($A20,1))) | C20: =IF($A20="","",SUMIFS('Inventário de Lotes'!$C:$C,'Inventário de Lotes'!$B:$B,">="&$A20,'Inventário de Lotes'!$B:$B,"<"&EDATE($A20,1))) | D20: =IF($A20="","",C20-B20) | E20: =IF($A20="","",COUNTIFS('Todos os Gastos'!$A:$A,">="&$A20,'Todos os Gastos'!$A:$A,"<"&EDATE($A20,1))) | F20: =IF($A20="","",COUNTIFS('Inventário de Lotes'!$B:$B,">="&$A20,'Inventário de Lotes'!$B:$B,"<"&EDATE($A20,1))) | G20: =IF($A20="","",SUM($D$4:D20))
A21: =IF(A20<$M$2,EDATE(A20,1),"") | B21: =IF($A21="","",SUMIFS('Todos os Gastos'!$C:$C,'Todos os Gastos'!$A:$A,">="&$A21,'Todos os Gastos'!$A:$A,"<"&EDATE($A21,1))) | C21: =IF($A21="","",SUMIFS('Inventário de Lotes'!$C:$C,'Inventário de Lotes'!$B:$B,">="&$A21,'Inventário de Lotes'!$B:$B,"<"&EDATE($A21,1))) | D21: =IF($A21="","",C21-B21) | E21: =IF($A21="","",COUNTIFS('Todos os Gastos'!$A:$A,">="&$A21,'Todos os Gastos'!$A:$A,"<"&EDATE($A21,1))) | F21: =IF($A21="","",COUNTIFS('Inventário de Lotes'!$B:$B,">="&$A21,'Inventário de Lotes'!$B:$B,"<"&EDATE($A21,1))) | G21: =IF($A21="","",SUM($D$4:D21))
A22: =IF(A21<$M$2,EDATE(A21,1),"") | B22: =IF($A22="","",SUMIFS('Todos os Gastos'!$C:$C,'Todos os Gastos'!$A:$A,">="&$A22,'Todos os Gastos'!$A:$A,"<"&EDATE($A22,1))) | C22: =IF($A22="","",SUMIFS('Inventário de Lotes'!$C:$C,'Inventário de Lotes'!$B:$B,">="&$A22,'Inventário de Lotes'!$B:$B,"<"&EDATE($A22,1))) | D22: =IF($A22="","",C22-B22) | E22: =IF($A22="","",COUNTIFS('Todos os Gastos'!$A:$A,">="&$A22,'Todos os Gastos'!$A:$A,"<"&EDATE($A22,1))) | F22: =IF($A22="","",COUNTIFS('Inventário de Lotes'!$B:$B,">="&$A22,'Inventário de Lotes'!$B:$B,"<"&EDATE($A22,1))) | G22: =IF($A22="","",SUM($D$4:D22))
A23: =IF(A22<$M$2,EDATE(A22,1),"") | B23: =IF($A23="","",SUMIFS('Todos os Gastos'!$C:$C,'Todos os Gastos'!$A:$A,">="&$A23,'Todos os Gastos'!$A:$A,"<"&EDATE($A23,1))) | C23: =IF($A23="","",SUMIFS('Inventário de Lotes'!$C:$C,'Inventário de Lotes'!$B:$B,">="&$A23,'Inventário de Lotes'!$B:$B,"<"&EDATE($A23,1))) | D23: =IF($A23="","",C23-B23) | E23: =IF($A23="","",COUNTIFS('Todos os Gastos'!$A:$A,">="&$A23,'Todos os Gastos'!$A:$A,"<"&EDATE($A23,1))) | F23: =IF($A23="","",COUNTIFS('Inventário de Lotes'!$B:$B,">="&$A23,'Inventário de Lotes'!$B:$B,"<"&EDATE($A23,1))) | G23: =IF($A23="","",SUM($D$4:D23))
A24: =IF(A23<$M$2,EDATE(A23,1),"") | B24: =IF($A24="","",SUMIFS('Todos os Gastos'!$C:$C,'Todos os Gastos'!$A:$A,">="&$A24,'Todos os Gastos'!$A:$A,"<"&EDATE($A24,1))) | C24: =IF($A24="","",SUMIFS('Inventário de Lotes'!$C:$C,'Inventário de Lotes'!$B:$B,">="&$A24,'Inventário de Lotes'!$B:$B,"<"&EDATE($A24,1))) | D24: =IF($A24="","",C24-B24) | E24: =IF($A24="","",COUNTIFS('Todos os Gastos'!$A:$A,">="&$A24,'Todos os Gastos'!$A:$A,"<"&EDATE($A24,1))) | F24: =IF($A24="","",COUNTIFS('Inventário de Lotes'!$B:$B,">="&$A24,'Inventário de Lotes'!$B:$B,"<"&EDATE($A24,1))) | G24: =IF($A24="","",SUM($D$4:D24))
... A123: =IF(A122<$M$2,EDATE(A122,1),"") | B123: =IF($A123="","",SUMIFS('Todos os Gastos'!$C:$C,'Todos os Gastos'!$A:$A,">="&$A123,'Todos os Gastos'!$A:$A,"<"&EDATE($A123,1))) | C123: =IF($A123="","",SUMIFS('Inventário de Lotes'!$C:$C,'Inventário de Lotes'!$B:$B,">="&$A123,'Inventário de Lotes'!$B:$B,"<"&EDATE($A123,1))) | D123: =IF($A123="","",C123-B123) | E123: =IF($A123="","",COUNTIFS('Todos os Gastos'!$A:$A,">="&$A123,'Todos os Gastos'!$A:$A,"<"&EDATE($A123,1))) | F123: =IF($A123="","",COUNTIFS('Inventário de Lotes'!$B:$B,">="&$A123,'Inventário de Lotes'!$B:$B,"<"&EDATE($A123,1))) | G123: =IF($A123="","",SUM($D$4:D123))

Sheet Carteiras
A1: Nome | B1: Taxa_Base_CDI | C1: Taxa_Bonus_CDI | D1: Dias_Bonus | E1: Prazo_Dias | F1: Carência_Dias | G1: Isento_IR | H1: Aplicação_Mínima | I1: Aplicação_Máxima | J1: Ativo | K1: Tipo | L1: Produto_Base | M1: Produto_Bonus | N1: Ratio_Base | O1: Ratio_Bonus | P1: Somente_Combo | Q1: Indexador | R1: FGC | S1: Observações | T1: Banco_Emissor | U1: Score_Banco | V1: Risco_Real | W1: Max_Usos | X1: Camada | Y1: Status_Confirmação | Z1: Campos_Pendentes
A2: ACE Capital Multicenários FC FIF MULT - RL | B2: 266.87 | C2: 0 | D2: 0 | E2: 1 | F2: 17 | G2: Não | H2: 100 | I2: pendente de confirmação | J2: Sim | K2: Fundo | P2: Não | Q2: Variável | R2: Não | S2: Rentab, bruta 12M 39,31%; Comparativo 266,87% do CDI; Aplicação D+0; Resgate D+15 corridos + liquidação D+2 úteis; Mov, mínima e saldo mínimo R$ 100; Horário 15h; Risco médio 16 | T2: ACE Capital | U2: pendente de confirmação | V2: Médio | W2: pendente de confirmação | X2: Fora da Carteira | Y2: Fortemente sustentado | Z2: Aplicação_Máxima, Score_Banco, Max_Usos
A3: ARX Fuji FIC de FIF RF CP RL | B3: 103.94 | C3: 0 | D3: 0 | E3: 1 | F3: 1 | G3: Não | H3: 1000 | I3: pendente de confirmação | J3: Sim | K3: Fundo | P3: Não | Q3: CDI | R3: Não | S3: Rentab, bruta 12M 15,31%; 103,94% do CDI; Aplicação D+0; Resgate D+0 + liquidação D+1; Mov, mínima e saldo mínimo R$ 1,000; Risco 4/baixo | T3: ARX | U3: pendente de confirmação | V3: Baixo | W3: pendente de confirmação | X3: Secundária | Y3: Fortemente sustentado | Z3: Aplicação_Máxima, Score_Banco, Max_Usos
A4: ARX SOBERANO FIRF REF DI RL | B4: 100 | C4: 0 | D4: 0 | E4: 1 | F4: 0 | G4: Não | H4: 1000 | I4: pendente de confirmação | J4: Sim | K4: Fundo | P4: Não | Q4: CDI | R4: Não | S4: PicPay 11/04/2026 | nome inferido de screenshot parcial | risco baixo | rentab, 12M 14,52% | 6M 6,99% | taxa proxy 100% CDI | prazo proxy 1 dia | T4: ARX | U4: pendente de confirmação | V4: Baixo | W4: pendente de confirmação | X4: Fora da Carteira | Y4: Fortemente sustentado | Z4: Aplicação_Máxima, Score_Banco, Max_Usos
A5: BTG CDB PLUS FIRF CP RL | B5: 100 | C5: 0 | D5: 0 | E5: 1 | F5: 0 | G5: Não | H5: 500 | I5: pendente de confirmação | J5: Sim | K5: Fundo | P5: Não | Q5: CDI | R5: Não | S5: PicPay 11/04/2026 | Fundo aberto | risco baixo | rentab, 12M 14,80% | 6M 7,10% | taxa proxy 100% CDI | prazo proxy 1 dia | T5: BTG | U5: pendente de confirmação | V5: Baixo | W5: pendente de confirmação | X5: Fora da Carteira | Y5: Fortemente sustentado | Z5: Aplicação_Máxima, Score_Banco, Max_Usos
A6: BTG Pactual Discovery FIM - Resp, Limitada - Classe Única | B6: 100 | C6: 0 | D6: 0 | E6: 1 | F6: 31 | G6: Não | H6: 5000 | I6: pendente de confirmação | J6: Sim | K6: Fundo | P6: Não | Q6: CDI | R6: Não | S6: Taxa adm, 2,00% a,a,; Cota de fechamento; Aplicação D+0; Resgate D+30 + liquidação D+1 útil; IR longo prazo; Risco médio | T6: BTG Pactual | U6: pendente de confirmação | V6: Médio | W6: pendente de confirmação | X6: Fora da Carteira | Y6: Fortemente sustentado | Z6: Aplicação_Máxima, Score_Banco, Max_Usos
A7: BTG YIELD FIRF REF CP RL | B7: 100 | C7: 0 | D7: 0 | E7: 1 | F7: 0 | G7: Não | H7: 500 | I7: pendente de confirmação | J7: Sim | K7: Fundo | P7: Não | Q7: CDI | R7: Não | S7: PicPay 11/04/2026 | Fundo aberto | risco baixo | rentab, 12M 14,72% | 6M 7,02% | taxa proxy 100% CDI | prazo proxy 1 dia | T7: BTG | U7: pendente de confirmação | V7: Baixo | W7: pendente de confirmação | X7: Fora da Carteira | Y7: Fortemente sustentado | Z7: Aplicação_Máxima, Score_Banco, Max_Usos
A8: CDB 3 Meses 100% CDI | B8: 100 | C8: 0 | D8: 0 | E8: 90 | F8: 90 | G8: Não | H8: 200 | I8: pendente de confirmação | J8: Não | K8: CDB | L8: pendente de confirmação | M8: pendente de confirmação | N8: pendente de confirmação | O8: pendente de confirmação | P8: Sim | Q8: CDI | R8: Sim | S8: Perna base do combo | T8: pendente de confirmação | U8: pendente de confirmação | V8: Médio | W8: pendente de confirmação | X8: Fora da Carteira | Y8: Pendente de confirmação | Z8: Aplicação_Máxima, Banco_Emissor, Produto_Base, Produto_Bonus, Ratio_Base, Ratio_Bonus, Score_Banco, Max_Usos
A9: CDB 6 Meses 100% CDI | B9: 100 | C9: 0 | D9: 0 | E9: 180 | F9: 180 | G9: Não | H9: 200 | I9: pendente de confirmação | J9: Não | K9: CDB | L9: pendente de confirmação | M9: pendente de confirmação | N9: pendente de confirmação | O9: pendente de confirmação | P9: Sim | Q9: CDI | R9: Sim | S9: Perna base do combo | T9: pendente de confirmação | U9: pendente de confirmação | V9: Médio | W9: pendente de confirmação | X9: Fora da Carteira | Y9: Pendente de confirmação | Z9: Aplicação_Máxima, Banco_Emissor, Produto_Base, Produto_Bonus, Ratio_Base, Ratio_Bonus, Score_Banco, Max_Usos
A10: CDB BMG DI 109% CDI - 1 ano | B10: 109 | C10: 0 | D10: 0 | E10: 365 | F10: 365 | G10: Não | H10: 100 | I10: pendente de confirmação | J10: Sim | K10: CDB | P10: Não | Q10: CDI | R10: Sim | S10: Resgate no vencimento; IR 17,5%; Perfil conservador; Risco baixo | T10: BMG | U10: pendente de confirmação | V10: Baixo | W10: pendente de confirmação | X10: Fora da Carteira | Y10: Fortemente sustentado | Z10: Aplicação_Máxima, Score_Banco, Max_Usos
A11: CDB BMG DI 110% CDI - 6 anos | B11: 110 | C11: 0 | D11: 0 | E11: 2190 | F11: 2190 | G11: Não | H11: 100 | I11: pendente de confirmação | J11: Sim | K11: CDB | P11: Não | Q11: CDI | R11: Sim | S11: Resgate no vencimento; IR 15%; Perfil moderado; Risco moderado | T11: BMG | U11: pendente de confirmação | V11: Moderado | W11: pendente de confirmação | X11: Fora da Carteira | Y11: Fortemente sustentado | Z11: Aplicação_Máxima, Score_Banco, Max_Usos
A12: CDB BMG DI 111% CDI - 2 anos | B12: 111 | C12: 0 | D12: 0 | E12: 730 | F12: 730 | G12: Não | H12: 100 | I12: pendente de confirmação | J12: Sim | K12: CDB | P12: Não | Q12: CDI | R12: Sim | S12: Resgate no vencimento; IR 15%; Perfil conservador; Risco baixo | T12: BMG | U12: pendente de confirmação | V12: Baixo | W12: pendente de confirmação | X12: Fora da Carteira | Y12: Fortemente sustentado | Z12: Aplicação_Máxima, Score_Banco, Max_Usos
A13: CDB BMG DI 112% CDI - 3 anos | B13: 112 | C13: 0 | D13: 0 | E13: 1095 | F13: 1095 | G13: Não | H13: 100 | I13: pendente de confirmação | J13: Sim | K13: CDB | P13: Não | Q13: CDI | R13: Sim | S13: Resgate no vencimento; IR 15%; Perfil conservador; Risco baixo | T13: BMG | U13: pendente de confirmação | V13: Baixo | W13: pendente de confirmação | X13: Fora da Carteira | Y13: Fortemente sustentado | Z13: Aplicação_Máxima, Score_Banco, Max_Usos
A14: CDB BMG DI 113% CDI - 4 anos | B14: 113 | C14: 0 | D14: 0 | E14: 1460 | F14: 1460 | G14: Não | H14: 100 | I14: pendente de confirmação | J14: Sim | K14: CDB | P14: Não | Q14: CDI | R14: Sim | S14: Resgate no vencimento; IR 15%; Perfil moderado; Risco moderado | T14: BMG | U14: pendente de confirmação | V14: Moderado | W14: pendente de confirmação | X14: Fora da Carteira | Y14: Fortemente sustentado | Z14: Aplicação_Máxima, Score_Banco, Max_Usos
A15: CDB BMG DI 114% CDI - 5 anos | B15: 114 | C15: 0 | D15: 0 | E15: 1825 | F15: 1825 | G15: Não | H15: 100 | I15: pendente de confirmação | J15: Sim | K15: CDB | P15: Não | Q15: CDI | R15: Sim | S15: Resgate no vencimento; IR 15%; Perfil moderado; Risco moderado | T15: BMG | U15: pendente de confirmação | V15: Moderado | W15: pendente de confirmação | X15: Fora da Carteira | Y15: Fortemente sustentado | Z15: Aplicação_Máxima, Score_Banco, Max_Usos
A16: CDB BMG DI Renda Mensal 108% CDI - 3 anos | B16: 108 | C16: 0 | D16: 0 | E16: 1095 | F16: 1095 | G16: Não | H16: pendente de confirmação | I16: pendente de confirmação | J16: Sim | K16: CDB | P16: Não | Q16: CDI | R16: Sim | S16: Pagamento de juros mensal; Resgate no vencimento; Perfil conservador; Risco baixo | T16: BMG | U16: pendente de confirmação | V16: Baixo | W16: pendente de confirmação | X16: Fora da Carteira | Y16: Fortemente sustentado | Z16: Aplicação_Mínima, Aplicação_Máxima, Score_Banco, Max_Usos
A17: CDB BMG Duplo Indexado - 2 anos | B17: 100 | C17: 13.16 | D17: 0 | E17: 730 | F17: 730 | G17: Não | H17: pendente de confirmação | I17: pendente de confirmação | J17: Sim | K17: CDB | P17: Não | Q17: CDI ou Pré | R17: Sim | S17: Alternativa: 100% do CDI ou prefixado 13,16% a,a,; Resgate no vencimento; IR 15%; Perfil conservador; Risco baixo | T17: BMG | U17: pendente de confirmação | V17: Baixo | W17: pendente de confirmação | X17: Fora da Carteira | Y17: Fortemente sustentado | Z17: Aplicação_Mínima, Aplicação_Máxima, Score_Banco, Max_Usos
A18: CDB BMG Duplo Indexado - 3 anos | B18: 100 | C18: 13.12 | D18: 0 | E18: 1095 | F18: 1095 | G18: Não | H18: pendente de confirmação | I18: pendente de confirmação | J18: Sim | K18: CDB | P18: Não | Q18: CDI ou Pré | R18: Sim | S18: Alternativa: 100% do CDI ou prefixado 13,12% a,a,; Resgate no vencimento; IR 15%; Perfil conservador; Risco baixo | T18: BMG | U18: pendente de confirmação | V18: Baixo | W18: pendente de confirmação | X18: Fora da Carteira | Y18: Fortemente sustentado | Z18: Aplicação_Mínima, Aplicação_Máxima, Score_Banco, Max_Usos
A19: CDB BMG Escalonado - até 109% CDI - 5 anos | B19: 105 | C19: 109 | D19: 0 | E19: 1825 | F19: 0 | G19: Não | H19: 50 | I19: pendente de confirmação | J19: Sim | K19: CDB | P19: Não | Q19: CDI Escalonado | R19: Sim | S19: Escalonamento: 1-360d 105% CDI; 361-720d 106%; 721-1080d 107%; 1081-1440d 108%; 1441-1825d 109%; Resgate diário; Perfil conservador; Risco baixo | T19: BMG | U19: pendente de confirmação | V19: Baixo | W19: pendente de confirmação | X19: Prioritária | Y19: Fortemente sustentado | Z19: Aplicação_Máxima, Score_Banco, Max_Usos
A20: CDB BMG IPCA+ 8,19% - 1 ano | B20: 8.19 | C20: 0 | D20: 0 | E20: 365 | F20: 365 | G20: Não | H20: 50 | I20: pendente de confirmação | J20: Sim | K20: CDB | P20: Não | Q20: IPCA+ | R20: Sim | S20: Resgate no vencimento; IR 17,5%; Perfil conservador; Risco baixo | T20: BMG | U20: pendente de confirmação | V20: Baixo | W20: pendente de confirmação | X20: Fora da Carteira | Y20: Fortemente sustentado | Z20: Aplicação_Máxima, Score_Banco, Max_Usos
A21: CDB BMG IPCA+ 8,65% - 5 anos | B21: 8.65 | C21: 0 | D21: 0 | E21: 1825 | F21: 1825 | G21: Não | H21: 50 | I21: pendente de confirmação | J21: Sim | K21: CDB | P21: Não | Q21: IPCA+ | R21: Sim | S21: Resgate no vencimento; IR 15%; Perfil moderado; Risco moderado | T21: BMG | U21: pendente de confirmação | V21: Moderado | W21: pendente de confirmação | X21: Fora da Carteira | Y21: Fortemente sustentado | Z21: Aplicação_Máxima, Score_Banco, Max_Usos
A22: CDB BMG IPCA+ 8,68% - 3 anos | B22: 8.68 | C22: 0 | D22: 0 | E22: 1095 | F22: 1095 | G22: Não | H22: 50 | I22: pendente de confirmação | J22: Sim | K22: CDB | P22: Não | Q22: IPCA+ | R22: Sim | S22: Resgate no vencimento; IR 15%; Perfil conservador; Risco baixo | T22: BMG | U22: pendente de confirmação | V22: Baixo | W22: pendente de confirmação | X22: Fora da Carteira | Y22: Fortemente sustentado | Z22: Aplicação_Máxima, Score_Banco, Max_Usos
A23: CDB BMG IPCA+ 8,69% - 4 anos | B23: 8.69 | C23: 0 | D23: 0 | E23: 1460 | F23: 1460 | G23: Não | H23: 50 | I23: pendente de confirmação | J23: Sim | K23: CDB | P23: Não | Q23: IPCA+ | R23: Sim | S23: Resgate no vencimento; IR 15%; Perfil moderado; Risco moderado | T23: BMG | U23: pendente de confirmação | V23: Moderado | W23: pendente de confirmação | X23: Fora da Carteira | Y23: Fortemente sustentado | Z23: Aplicação_Máxima, Score_Banco, Max_Usos
A24: CDB BMG IPCA+ 9,01% - 2 anos | B24: 9.01 | C24: 0 | D24: 0 | E24: 730 | F24: 730 | G24: Não | H24: 50 | I24: pendente de confirmação | J24: Sim | K24: CDB | P24: Não | Q24: IPCA+ | R24: Sim | S24: Resgate no vencimento; IR 15%; Perfil conservador; Risco baixo | T24: BMG | U24: pendente de confirmação | V24: Baixo | W24: pendente de confirmação | X24: Prioritária | Y24: Fortemente sustentado | Z24: Aplicação_Máxima, Score_Banco, Max_Usos
A25: CDB BMG Pré 14,70% - 1 ano | B25: 14.7 | C25: 0 | D25: 0 | E25: 365 | F25: 365 | G25: Não | H25: 50 | I25: pendente de confirmação | J25: Sim | K25: CDB | P25: Não | Q25: Pré | R25: Sim | S25: Resgate no vencimento; IR 17,5%; Perfil conservador; Risco baixo | T25: BMG | U25: pendente de confirmação | V25: Baixo | W25: pendente de confirmação | X25: Fora da Carteira | Y25: Fortemente sustentado | Z25: Aplicação_Máxima, Score_Banco, Max_Usos
A26: CDB BMG Pré 14,84% - 3 anos | B26: 14.84 | C26: 0 | D26: 0 | E26: 1095 | F26: 1095 | G26: Não | H26: 50 | I26: pendente de confirmação | J26: Sim | K26: CDB | P26: Não | Q26: Pré | R26: Sim | S26: Resgate no vencimento; IR 15%; Perfil conservador; Risco baixo | T26: BMG | U26: pendente de confirmação | V26: Baixo | W26: pendente de confirmação | X26: Fora da Carteira | Y26: Fortemente sustentado | Z26: Aplicação_Máxima, Score_Banco, Max_Usos
A27: CDB BMG Pré 14,88% - 2 anos | B27: 14.88 | C27: 0 | D27: 0 | E27: 730 | F27: 730 | G27: Não | H27: 50 | I27: pendente de confirmação | J27: Sim | K27: CDB | P27: Não | Q27: Pré | R27: Sim | S27: Resgate no vencimento; IR 15%; Perfil conservador; Risco baixo | T27: BMG | U27: pendente de confirmação | V27: Baixo | W27: pendente de confirmação | X27: Fora da Carteira | Y27: Fortemente sustentado | Z27: Aplicação_Máxima, Score_Banco, Max_Usos
A28: CDB BMG Pré 14,90% - 4 anos | B28: 14.9 | C28: 0 | D28: 0 | E28: 1460 | F28: 1460 | G28: Não | H28: 50 | I28: pendente de confirmação | J28: Sim | K28: CDB | P28: Não | Q28: Pré | R28: Sim | S28: Resgate no vencimento; IR 15%; Perfil moderado; Risco moderado | T28: BMG | U28: pendente de confirmação | V28: Moderado | W28: pendente de confirmação | X28: Fora da Carteira | Y28: Fortemente sustentado | Z28: Aplicação_Máxima, Score_Banco, Max_Usos
A29: CDB BMG Pré 14,96% - 5 anos | B29: 14.96 | C29: 0 | D29: 0 | E29: 1825 | F29: 1825 | G29: Não | H29: 50 | I29: pendente de confirmação | J29: Sim | K29: CDB | P29: Não | Q29: Pré | R29: Sim | S29: Resgate no vencimento; IR 15%; Perfil moderado; Risco moderado | T29: BMG | U29: pendente de confirmação | V29: Moderado | W29: pendente de confirmação | X29: Fora da Carteira | Y29: Fortemente sustentado | Z29: Aplicação_Máxima, Score_Banco, Max_Usos
A30: CDB BMG Super Poupança | B30: 107 | C30: 0 | D30: 0 | E30: 1096 | F30: 0 | G30: Não | H30: 50 | I30: 500000000 | J30: Sim | K30: CDB | P30: Não | Q30: Selic | R30: Sim | S30: Emissor: BMG | 107,00% da Selic | prazo 1096 dias | carência 0 dias | aplicação mínima R$ 50,00 | aplicação máxima R$ 500,000,000,00 | FGC | T30: BMG | U30: pendente de confirmação | V30: Médio | W30: pendente de confirmação | X30: Prioritária | Y30: Confirmado | Z30: Score_Banco, Max_Usos
A31: CDB BTG 15,00% Prefixado | B31: 15 | C31: 0 | D31: 0 | E31: 90 | F31: 90 | G31: Não | H31: 1000 | I31: pendente de confirmação | J31: Sim | K31: CDB | P31: Não | Q31: Prefixado | R31: Sim | S31: Oportunidade BTG | T31: BTG | U31: pendente de confirmação | V31: Baixo | W31: pendente de confirmação | X31: Fora da Carteira | Y31: Fortemente sustentado | Z31: Aplicação_Máxima, Score_Banco, Max_Usos
A32: CDB Daycoval 104% | B32: 104 | C32: 0 | D32: 0 | E32: 720 | F32: 0 | G32: Não | H32: 1000 | I32: pendente de confirmação | J32: Sim | K32: CDB | P32: Não | Q32: CDI | R32: Sim | S32: Emissor: Daycoval | 104,00% do CDI | prazo 720 dias | carência 0 dias | aplicação mínima R$ 1,000,00 | FGC | T32: Daycoval | U32: pendente de confirmação | V32: Baixo | W32: pendente de confirmação | X32: Secundária | Y32: Fortemente sustentado | Z32: Aplicação_Máxima, Score_Banco, Max_Usos
A33: CDB Digimais 140% | B33: 140 | C33: 0 | D33: 0 | E33: 360 | F33: 360 | G33: Não | H33: 1000 | I33: pendente de confirmação | J33: Sim | K33: CDB | P33: Não | Q33: CDI | R33: Sim | S33: Taxa fixa alta | T33: Digimais | U33: pendente de confirmação | V33: Médio | W33: pendente de confirmação | X33: Fora da Carteira | Y33: Fortemente sustentado | Z33: Aplicação_Máxima, Score_Banco, Max_Usos
A34: CDB InfinitePay 106% | B34: 106 | C34: 0 | D34: 0 | E34: 91 | F34: 31 | G34: Não | H34: 1 | I34: pendente de confirmação | J34: Sim | K34: CDB | P34: Não | Q34: CDI | R34: Sim | S34: Emissor: InfinitePay | 106,00% do CDI | prazo 91 dias | carência 31 dias | aplicação mínima R$ 1,00 | FGC | T34: InfinitePay | U34: pendente de confirmação | V34: Médio | W34: pendente de confirmação | X34: Secundária | Y34: Fortemente sustentado | Z34: Aplicação_Máxima, Score_Banco, Max_Usos
A35: CDB IPCA+ 7,90% 3 anos | B35: 7.9 | C35: 0 | D35: 0 | E35: 1080 | F35: 1080 | G35: Não | H35: 1000 | I35: pendente de confirmação | J35: Sim | K35: CDB | P35: Não | Q35: IPCA | R35: Sim | S35: Emissor: Genérico FGC | IPCA + 7,90% | prazo 1080 dias | carência 1080 dias | aplicação mínima R$ 1,000,00 | FGC | T35: pendente de confirmação | U35: pendente de confirmação | V35: Médio | W35: pendente de confirmação | X35: Fora da Carteira | Y35: Pendente de confirmação | Z35: Aplicação_Máxima, Banco_Emissor, Score_Banco, Max_Usos
A36: CDB IPCA+ 8,34% 2 anos | B36: 8.3 | C36: 0 | D36: 0 | E36: 720 | F36: 720 | G36: Não | H36: 1000 | I36: pendente de confirmação | J36: Sim | K36: CDB | P36: Não | Q36: IPCA | R36: Sim | S36: Emissor: Genérico FGC | IPCA + 8,30% | prazo 720 dias | carência 720 dias | aplicação mínima R$ 1,000,00 | FGC | T36: pendente de confirmação | U36: pendente de confirmação | V36: Médio | W36: pendente de confirmação | X36: Fora da Carteira | Y36: Pendente de confirmação | Z36: Aplicação_Máxima, Banco_Emissor, Score_Banco, Max_Usos
A37: CDB Liquidez Diária 103% | B37: 103 | C37: 0 | D37: 0 | E37: 730 | F37: 1 | G37: Não | H37: 1 | I37: 10000000 | J37: Sim | K37: CDB | P37: Não | Q37: CDI | R37: Sim | S37: PagBank 11/04/2026 | BancoSeguro | 103,00% do CDI | vencimento 11/04/2028 | resgate diário | carência até 12/04/2026 | vencimento antecipado opcional pelo PagBank | aplicação mínima R$ 1,00 | aplicação máxima R$ 10,000,000,00 | T37: pendente de confirmação | U37: pendente de confirmação | V37: Muito Baixo | W37: pendente de confirmação | X37: Fora da Carteira | Y37: Fortemente sustentado | Z37: Banco_Emissor, Score_Banco, Max_Usos
A38: CDB Neon Cofrinho Escalonado - 100% a 113% CDI | B38: 100 | C38: 113 | D38: 0 | E38: 730 | F38: 0 | G38: Não | H38: 1 | I38: pendente de confirmação | J38: Sim | K38: CDB | P38: Não | Q38: CDI Escalonado | R38: Sim | S38: Resgate 24h por dia; Rende a partir do 31º dia; Escalonamento: 0-30d 0,01% CDI; 1-6m 100%; 6-12m 103%; 12-18m 106%; 18-24m 109%; acima de 24m 113%; Rentabilidade máxima a partir de 2 anos; Risco baixo | T38: Neon | U38: pendente de confirmação | V38: Baixo | W38: pendente de confirmação | X38: Fora da Carteira | Y38: Fortemente sustentado | Z38: Aplicação_Máxima, Score_Banco, Max_Usos
A39: CDB Neon Diário Escalonado | B39: 113 | C39: 0 | D39: 0 | E39: 1095 | F39: 0 | G39: Não | H39: 1 | I39: 250000 | J39: Sim | K39: CDB | P39: Não | Q39: CDI | R39: Sim | S39: Escalonado até 113% | T39: Neon | U39: pendente de confirmação | V39: Baixo | W39: pendente de confirmação | X39: Fora da Carteira | Y39: Confirmado | Z39: Score_Banco, Max_Usos
A40: CDB Neon Planejado 112% CDI - 90 dias | B40: 112 | C40: 0 | D40: 0 | E40: 90 | F40: 90 | G40: Não | H40: 100 | I40: 500000 | J40: Sim | K40: CDB | P40: Não | Q40: CDI | R40: Sim | S40: Vencimento 11/07/2026; Rendimento desde o 1º dia útil; Após o vencimento rende 100% CDI com resgate 24h; Risco baixo | T40: Neon | U40: pendente de confirmação | V40: Baixo | W40: pendente de confirmação | X40: Prioritária | Y40: Confirmado | Z40: Score_Banco, Max_Usos
A41: CDB Neon Planejado 116% CDI - 181 dias | B41: 116 | C41: 0 | D41: 0 | E41: 181 | F41: 181 | G41: Não | H41: 100 | I41: 500000 | J41: Sim | K41: CDB | P41: Não | Q41: CDI | R41: Sim | S41: Vencimento 10/10/2026; Rendimento desde o 1º dia útil; Após o vencimento rende 100% CDI com resgate 24h; Risco baixo | T41: Neon | U41: pendente de confirmação | V41: Baixo | W41: pendente de confirmação | X41: Prioritária | Y41: Confirmado | Z41: Score_Banco, Max_Usos
A42: CDB Neon Planejado 119% CDI - 361 dias | B42: 119 | C42: 0 | D42: 0 | E42: 361 | F42: 361 | G42: Não | H42: 100 | I42: 500000 | J42: Sim | K42: CDB | P42: Não | Q42: CDI | R42: Sim | S42: Vencimento 08/04/2027; Rendimento desde o 1º dia útil; Após o vencimento rende 100% CDI com resgate 24h; Risco baixo | T42: Neon | U42: pendente de confirmação | V42: Baixo | W42: pendente de confirmação | X42: Prioritária | Y42: Confirmado | Z42: Score_Banco, Max_Usos
A43: CDB Neon Planejado 120% CDI - 721 dias | B43: 120 | C43: 0 | D43: 0 | E43: 721 | F43: 721 | G43: Não | H43: 100 | I43: 500000 | J43: Sim | K43: CDB | P43: Não | Q43: CDI | R43: Sim | S43: Vencimento 02/04/2028; Rendimento desde o 1º dia útil; Após o vencimento rende 100% CDI com resgate 24h; Risco baixo | T43: Neon | U43: pendente de confirmação | V43: Baixo | W43: pendente de confirmação | X43: Prioritária | Y43: Confirmado | Z43: Score_Banco, Max_Usos
A44: CDB Neon Planejado 150% CDI - 60 dias | B44: 150 | C44: 0 | D44: 0 | E44: 60 | F44: 60 | G44: Não | H44: 100 | I44: 20000 | J44: Sim | K44: CDB | P44: Não | Q44: CDI | R44: Sim | S44: Vencimento 11/06/2026; Rendimento desde o 1º dia útil; Após o vencimento rende 100% CDI com resgate 24h; Risco baixo | T44: Neon | U44: pendente de confirmação | V44: Baixo | W44: pendente de confirmação | X44: Prioritária | Y44: Confirmado | Z44: Score_Banco, Max_Usos
A45: CDB Neon Resgate Diário 100% CDI | B45: 100 | C45: 0 | D45: 0 | E45: 1095 | F45: 0 | G45: Não | H45: 1 | I45: pendente de confirmação | J45: Sim | K45: CDB | P45: Não | Q45: CDI | R45: Sim | S45: Vencimento 27/03/2029; Resgate 24h por dia; Rendimento desde o 1º dia útil; Risco baixo | T45: Neon | U45: pendente de confirmação | V45: Baixo | W45: pendente de confirmação | X45: Fora da Carteira | Y45: Fortemente sustentado | Z45: Aplicação_Máxima, Score_Banco, Max_Usos
A46: CDB PagBank 104% | B46: 104 | C46: 0 | D46: 0 | E46: 90 | F46: 90 | G46: Não | H46: 1 | I46: 10000000 | J46: Sim | K46: CDB | P46: Não | Q46: CDI | R46: Sim | S46: PagBank 11/04/2026 | BancoSeguro | 104,00% do CDI | vencimento 10/07/2026 | resgate no vencimento | carência até 10/07/2026 | vencimento antecipado opcional pelo PagBank | aplicação mínima R$ 1,00 | aplicação máxima R$ 10,000,000,00 | T46: pendente de confirmação | U46: pendente de confirmação | V46: Muito Baixo | W46: pendente de confirmação | X46: Fora da Carteira | Y46: Fortemente sustentado | Z46: Banco_Emissor, Score_Banco, Max_Usos
A47: CDB PagBank 105% | B47: 105 | C47: 0 | D47: 0 | E47: 180 | F47: 180 | G47: Não | H47: 500 | I47: 10000000 | J47: Sim | K47: CDB | P47: Não | Q47: CDI | R47: Sim | S47: PagBank 11/04/2026 | BancoSeguro | 105,00% do CDI | vencimento 09/10/2026 | resgate no vencimento | carência até 09/10/2026 | vencimento antecipado opcional pelo PagBank | aplicação mínima R$ 500,00 | aplicação máxima R$ 10,000,000,00 | T47: pendente de confirmação | U47: pendente de confirmação | V47: Muito Baixo | W47: pendente de confirmação | X47: Fora da Carteira | Y47: Fortemente sustentado | Z47: Banco_Emissor, Score_Banco, Max_Usos
A48: CDB PagBank 106% | B48: 106 | C48: 0 | D48: 0 | E48: 365 | F48: 365 | G48: Não | H48: 500 | I48: 10000000 | J48: Sim | K48: CDB | P48: Não | Q48: CDI | R48: Sim | S48: PagBank 11/04/2026 | BancoSeguro | 106,00% do CDI | vencimento 11/04/2027 | resgate no vencimento | carência até 11/04/2027 | vencimento antecipado opcional pelo PagBank | aplicação mínima R$ 500,00 | aplicação máxima R$ 10,000,000,00 | T48: pendente de confirmação | U48: pendente de confirmação | V48: Muito Baixo | W48: pendente de confirmação | X48: Fora da Carteira | Y48: Fortemente sustentado | Z48: Banco_Emissor, Score_Banco, Max_Usos
A49: CDB PagBank 107,50% | B49: 107.5 | C49: 0 | D49: 0 | E49: 1095 | F49: 1095 | G49: Não | H49: 500 | I49: 10000000 | J49: Sim | K49: CDB | P49: Não | Q49: CDI | R49: Sim | S49: PagBank 11/04/2026 | BancoSeguro | 107,50% do CDI | vencimento 11/04/2029 | resgate no vencimento | carência até 11/04/2029 | vencimento antecipado opcional pelo PagBank | aplicação mínima R$ 500,00 | aplicação máxima R$ 10,000,000,00 | T49: pendente de confirmação | U49: pendente de confirmação | V49: Baixo | W49: pendente de confirmação | X49: Fora da Carteira | Y49: Fortemente sustentado | Z49: Banco_Emissor, Score_Banco, Max_Usos
A50: CDB PagBank 107% | B50: 107 | C50: 0 | D50: 0 | E50: 720 | F50: 720 | G50: Não | H50: 500 | I50: 10000000 | J50: Sim | K50: CDB | P50: Não | Q50: CDI | R50: Sim | S50: PagBank 11/04/2026 | BancoSeguro | 107,00% do CDI | vencimento 01/04/2028 | resgate no vencimento | carência até 01/04/2028 | vencimento antecipado opcional pelo PagBank | aplicação mínima R$ 500,00 | aplicação máxima R$ 10,000,000,00 | T50: pendente de confirmação | U50: pendente de confirmação | V50: Muito Baixo | W50: pendente de confirmação | X50: Fora da Carteira | Y50: Fortemente sustentado | Z50: Banco_Emissor, Score_Banco, Max_Usos
A51: CDB PagBank 108,50% | B51: 108.5 | C51: 0 | D51: 0 | E51: 1460 | F51: 1460 | G51: Não | H51: 500 | I51: 10000000 | J51: Sim | K51: CDB | P51: Não | Q51: CDI | R51: Sim | S51: PagBank 11/04/2026 | BancoSeguro | 108,50% do CDI | vencimento 11/04/2030 | resgate no vencimento | carência até 11/04/2030 | vencimento antecipado opcional pelo PagBank | aplicação mínima R$ 500,00 | aplicação máxima R$ 10,000,000,00 | T51: pendente de confirmação | U51: pendente de confirmação | V51: Baixo | W51: pendente de confirmação | X51: Fora da Carteira | Y51: Fortemente sustentado | Z51: Banco_Emissor, Score_Banco, Max_Usos
A52: CDB PagBank 14,80% | B52: 14.8 | C52: 0 | D52: 0 | E52: 720 | F52: 720 | G52: Não | H52: 500 | I52: 10000000 | J52: Sim | K52: CDB | P52: Não | Q52: Prefixado | R52: Sim | S52: PagBank 11/04/2026 | BancoSeguro | 14,80% a,a, | vencimento 01/04/2028 | resgate no vencimento | carência até 01/04/2028 | vencimento antecipado opcional pelo PagBank | aplicação mínima R$ 500,00 | aplicação máxima R$ 10,000,000,00 | T52: pendente de confirmação | U52: pendente de confirmação | V52: Muito Baixo | W52: pendente de confirmação | X52: Fora da Carteira | Y52: Fortemente sustentado | Z52: Banco_Emissor, Score_Banco, Max_Usos
A53: CDB PagBank 14,90% | B53: 14.9 | C53: 0 | D53: 0 | E53: 365 | F53: 365 | G53: Não | H53: 500 | I53: 10000000 | J53: Sim | K53: CDB | P53: Não | Q53: Prefixado | R53: Sim | S53: PagBank 11/04/2026 | BancoSeguro | 14,90% a,a, prefixado | vencimento 11/04/2027 | resgate no vencimento | carência até 11/04/2027 | vencimento antecipado opcional pelo PagBank | aplicação mínima R$ 500,00 | aplicação máxima R$ 10,000,000,00 | T53: pendente de confirmação | U53: pendente de confirmação | V53: Muito Baixo | W53: pendente de confirmação | X53: Secundária | Y53: Fortemente sustentado | Z53: Banco_Emissor, Score_Banco, Max_Usos
A54: CDB PagBank 15,00% | B54: 15 | C54: 0 | D54: 0 | E54: 180 | F54: 180 | G54: Não | H54: 500 | I54: 10000000 | J54: Sim | K54: CDB | P54: Não | Q54: Prefixado | R54: Sim | S54: PagBank 11/04/2026 | BancoSeguro | 15,00% a,a, prefixado | vencimento 09/10/2026 | resgate no vencimento | carência até 09/10/2026 | vencimento antecipado opcional pelo PagBank | aplicação mínima R$ 500,00 | aplicação máxima R$ 10,000,000,00 | T54: pendente de confirmação | U54: pendente de confirmação | V54: Muito Baixo | W54: pendente de confirmação | X54: Fora da Carteira | Y54: Fortemente sustentado | Z54: Banco_Emissor, Score_Banco, Max_Usos
A55: CDB PagBank 3 Meses | B55: 102.25 | C55: 0 | D55: 0 | E55: 90 | F55: 90 | G55: Não | H55: 100 | I55: 10000000 | J55: Sim | K55: CDB | P55: Não | Q55: CDI | R55: Sim | S55: PagBank 11/04/2026 | BancoSeguro | 102,25% do CDI | vencimento 14/07/2026 | resgate no vencimento | carência até 14/07/2026 | aplicação mínima R$ 100,00 | aplicação máxima R$ 10,000,000,00 | T55: pendente de confirmação | U55: pendente de confirmação | V55: Muito Baixo | W55: pendente de confirmação | X55: Fora da Carteira | Y55: Fortemente sustentado | Z55: Banco_Emissor, Score_Banco, Max_Usos
A56: CDB PagBank IPCA+ 8,30% | B56: 8.3 | C56: 0 | D56: 0 | E56: 720 | F56: 720 | G56: Não | H56: 500 | I56: 10000000 | J56: Sim | K56: CDB | P56: Não | Q56: IPCA | R56: Sim | S56: PagBank 11/04/2026 | BancoSeguro | IPCA + 8,30% a,a, | vencimento 01/04/2028 | resgate no vencimento | carência até 01/04/2028 | vencimento antecipado opcional pelo PagBank | aplicação mínima R$ 500,00 | aplicação máxima R$ 10,000,000,00 | T56: pendente de confirmação | U56: pendente de confirmação | V56: Muito Baixo | W56: pendente de confirmação | X56: Fora da Carteira | Y56: Fortemente sustentado | Z56: Banco_Emissor, Score_Banco, Max_Usos
A57: CDB PagBank IPCA+ 8,40% | B57: 8.4 | C57: 0 | D57: 0 | E57: 365 | F57: 365 | G57: Não | H57: 500 | I57: 10000000 | J57: Sim | K57: CDB | P57: Não | Q57: IPCA | R57: Sim | S57: PagBank 11/04/2026 | BancoSeguro | IPCA + 8,40% a,a, | vencimento 11/04/2027 | resgate no vencimento | carência até 11/04/2027 | vencimento antecipado opcional pelo PagBank | aplicação mínima R$ 500,00 | aplicação máxima R$ 10,000,000,00 | T57: pendente de confirmação | U57: pendente de confirmação | V57: Muito Baixo | W57: pendente de confirmação | X57: Secundária | Y57: Fortemente sustentado | Z57: Banco_Emissor, Score_Banco, Max_Usos
A58: CDB PagBank Liquidez | B58: 102 | C58: 0 | D58: 0 | E58: 1440 | F58: 0 | G58: Não | H58: 100 | I58: 10000000 | J58: Sim | K58: CDB | P58: Não | Q58: CDI | R58: Sim | S58: PagBank 11/04/2026 | BancoSeguro | 102,00% do CDI | vencimento 21/03/2030 | resgate imediato | aplicação mínima R$ 100,00 | aplicação máxima R$ 10,000,000,00 | T58: pendente de confirmação | U58: pendente de confirmação | V58: Muito Baixo | W58: pendente de confirmação | X58: Fora da Carteira | Y58: Fortemente sustentado | Z58: Banco_Emissor, Score_Banco, Max_Usos
A59: CDB PicPay 100% | B59: 100 | C59: 0 | D59: 0 | E59: 90 | F59: 90 | G59: Não | H59: 200 | I59: pendente de confirmação | J59: Não | K59: CDB | L59: pendente de confirmação | M59: pendente de confirmação | N59: pendente de confirmação | O59: pendente de confirmação | P59: Sim | Q59: CDI | R59: Sim | S59: PicPay 11/04/2026 | CDB base do combo 100% do CDI | vencimento em 3 meses (13/07/2026 na captura) | aplicação mínima R$ 200,00 | FGC | produto usado para desbloquear a oferta de 115% do CDI | T59: PicPay Bank | U59: pendente de confirmação | V59: Baixo | W59: pendente de confirmação | X59: Fora da Carteira | Y59: Pendente de confirmação | Z59: Aplicação_Máxima, Produto_Base, Produto_Bonus, Ratio_Base, Ratio_Bonus, Score_Banco, Max_Usos
A60: CDB PicPay 115% | B60: 115 | C60: 0 | D60: 0 | E60: 90 | F60: 90 | G60: Não | H60: 100 | I60: pendente de confirmação | J60: Não | K60: CDB | L60: pendente de confirmação | M60: pendente de confirmação | N60: pendente de confirmação | O60: pendente de confirmação | P60: Sim | Q60: CDI | R60: Sim | S60: PicPay 11/04/2026 | oferta bônus de combo a 115% do CDI | cada R$ 200,00 investidos no CDB base 100% libera R$ 100,00 para esta perna bônus | prazo não apareceu de forma isolada na captura; mantido em 3 meses por contexto do combo | T60: PicPay Bank | U60: pendente de confirmação | V60: Baixo | W60: pendente de confirmação | X60: Fora da Carteira | Y60: Pendente de confirmação | Z60: Aplicação_Máxima, Produto_Base, Produto_Bonus, Ratio_Base, Ratio_Bonus, Score_Banco, Max_Usos
A61: CDB PicPay 120% 3 Meses | B61: 120 | C61: 0 | D61: 0 | E61: 90 | F61: 90 | G61: Não | H61: 100 | I61: pendente de confirmação | J61: Não | K61: CDB | L61: pendente de confirmação | M61: pendente de confirmação | N61: pendente de confirmação | O61: pendente de confirmação | P61: Sim | Q61: CDI | R61: Sim | S61: PicPay 11/04/2026 | oferta condicional/indisponível no momento | 120% do CDI | vencimento 13/07/2026 | botão orienta investir no CDB 3 meses 100% do CDI para acessar a oferta | T61: PicPay Bank | U61: pendente de confirmação | V61: Baixo | W61: pendente de confirmação | X61: Fora da Carteira | Y61: Pendente de confirmação | Z61: Aplicação_Máxima, Produto_Base, Produto_Bonus, Ratio_Base, Ratio_Bonus, Score_Banco, Max_Usos
A62: CDB PicPay 120% 6 Meses | B62: 120 | C62: 0 | D62: 0 | E62: 180 | F62: 180 | G62: Não | H62: 100 | I62: pendente de confirmação | J62: Não | K62: CDB | L62: pendente de confirmação | M62: pendente de confirmação | N62: pendente de confirmação | O62: pendente de confirmação | P62: Sim | Q62: CDI | R62: Sim | S62: PicPay 11/04/2026 | oferta condicional/indisponível no momento | 120% do CDI | vencimento 13/10/2026 | botão orienta investir no CDB 6 meses 100% do CDI para acessar a oferta | T62: PicPay Bank | U62: pendente de confirmação | V62: Baixo | W62: pendente de confirmação | X62: Fora da Carteira | Y62: Pendente de confirmação | Z62: Aplicação_Máxima, Produto_Base, Produto_Bonus, Ratio_Base, Ratio_Bonus, Score_Banco, Max_Usos
A63: CDB PicPay Bank 1 Ano | B63: 106 | C63: 0 | D63: 0 | E63: 365 | F63: 365 | G63: Não | H63: 100 | I63: pendente de confirmação | J63: Sim | K63: CDB | P63: Não | Q63: CDI | R63: Sim | S63: PicPay 11/04/2026 | 106,00% do CDI | vencimento 12/04/2027 | resgate no vencimento | aplicação mínima R$ 100,00 | houve screenshot adicional com 13/04/2027; mantido um único registro para evitar duplicidade | T63: PicPay Bank | U63: pendente de confirmação | V63: Baixo | W63: pendente de confirmação | X63: Fora da Carteira | Y63: Fortemente sustentado | Z63: Aplicação_Máxima, Score_Banco, Max_Usos
A64: CDB PicPay Bank 18 Meses | B64: 107.25 | C64: 0 | D64: 0 | E64: 540 | F64: 540 | G64: Não | H64: 100 | I64: pendente de confirmação | J64: Sim | K64: CDB | P64: Não | Q64: CDI | R64: Sim | S64: PicPay 11/04/2026 | 107,25% do CDI | vencimento 13/10/2027 | resgate no vencimento | aplicação mínima R$ 100,00 | T64: PicPay Bank | U64: pendente de confirmação | V64: Baixo | W64: pendente de confirmação | X64: Fora da Carteira | Y64: Fortemente sustentado | Z64: Aplicação_Máxima, Score_Banco, Max_Usos
A65: CDB PicPay Bank 2 Anos | B65: 108 | C65: 0 | D65: 0 | E65: 730 | F65: 730 | G65: Não | H65: 100 | I65: pendente de confirmação | J65: Sim | K65: CDB | P65: Não | Q65: CDI | R65: Sim | S65: PicPay 11/04/2026 | 108,00% do CDI | vencimento 12/04/2028 | resgate no vencimento | aplicação mínima R$ 100,00 | houve screenshot adicional com 13/04/2028; mantido um único registro para evitar duplicidade | T65: PicPay Bank | U65: pendente de confirmação | V65: Baixo | W65: pendente de confirmação | X65: Secundária | Y65: Fortemente sustentado | Z65: Aplicação_Máxima, Score_Banco, Max_Usos
A66: CDB PicPay Bank 3 Anos | B66: 108.75 | C66: 0 | D66: 0 | E66: 1095 | F66: 1095 | G66: Não | H66: 100 | I66: pendente de confirmação | J66: Sim | K66: CDB | P66: Não | Q66: CDI | R66: Sim | S66: PicPay 11/04/2026 | 108,75% do CDI | vencimento 12/04/2029 | resgate no vencimento | aplicação mínima R$ 100,00 | T66: PicPay Bank | U66: pendente de confirmação | V66: Baixo | W66: pendente de confirmação | X66: Fora da Carteira | Y66: Fortemente sustentado | Z66: Aplicação_Máxima, Score_Banco, Max_Usos
A67: CDB PicPay Bank 3 Meses | B67: 102.25 | C67: 0 | D67: 0 | E67: 90 | F67: 90 | G67: Não | H67: 100 | I67: pendente de confirmação | J67: Sim | K67: CDB | P67: Não | Q67: CDI | R67: Sim | S67: PicPay 11/04/2026 | 102,25% do CDI | vencimento 14/07/2026 | resgate no vencimento | aplicação mínima R$ 100,00 | T67: PicPay Bank | U67: pendente de confirmação | V67: Baixo | W67: pendente de confirmação | X67: Fora da Carteira | Y67: Fortemente sustentado | Z67: Aplicação_Máxima, Score_Banco, Max_Usos
A68: CDB PicPay Bank 4 Anos | B68: 109 | C68: 0 | D68: 0 | E68: 1460 | F68: 1460 | G68: Não | H68: 100 | I68: pendente de confirmação | J68: Sim | K68: CDB | P68: Não | Q68: CDI | R68: Sim | S68: PicPay 11/04/2026 | 109,00% do CDI | vencimento 12/04/2030 | resgate no vencimento | aplicação mínima R$ 100,00 | T68: PicPay Bank | U68: pendente de confirmação | V68: Baixo | W68: pendente de confirmação | X68: Fora da Carteira | Y68: Fortemente sustentado | Z68: Aplicação_Máxima, Score_Banco, Max_Usos
A69: CDB PicPay Bank 5 Anos | B69: 110 | C69: 0 | D69: 0 | E69: 1825 | F69: 1825 | G69: Não | H69: 100 | I69: pendente de confirmação | J69: Sim | K69: CDB | P69: Não | Q69: CDI | R69: Sim | S69: PicPay 11/04/2026 | 110,00% do CDI | vencimento 15/04/2031 | resgate no vencimento | aplicação mínima R$ 100,00 | T69: PicPay Bank | U69: pendente de confirmação | V69: Baixo | W69: pendente de confirmação | X69: Fora da Carteira | Y69: Fortemente sustentado | Z69: Aplicação_Máxima, Score_Banco, Max_Usos
A70: CDB PicPay Bank 6 Meses | B70: 103.25 | C70: 0 | D70: 0 | E70: 180 | F70: 180 | G70: Não | H70: 100 | I70: pendente de confirmação | J70: Sim | K70: CDB | P70: Não | Q70: CDI | R70: Sim | S70: PicPay 11/04/2026 | 103,25% do CDI | vencimento 14/10/2026 | resgate no vencimento | aplicação mínima R$ 100,00 | T70: PicPay Bank | U70: pendente de confirmação | V70: Baixo | W70: pendente de confirmação | X70: Fora da Carteira | Y70: Fortemente sustentado | Z70: Aplicação_Máxima, Score_Banco, Max_Usos
A71: CDB PicPay Bank Liquidez | B71: 102 | C71: 0 | D71: 0 | E71: 1440 | F71: 0 | G71: Não | H71: 100 | I71: pendente de confirmação | J71: Sim | K71: CDB | P71: Não | Q71: CDI | R71: Sim | S71: PicPay 11/04/2026 | 102,00% do CDI | vencimento 21/03/2030 | resgate imediato | aplicação mínima R$ 100,00 | T71: PicPay Bank | U71: pendente de confirmação | V71: Baixo | W71: pendente de confirmação | X71: Fora da Carteira | Y71: Fortemente sustentado | Z71: Aplicação_Máxima, Score_Banco, Max_Usos
A72: CDB Pine IPCA+ 8,5% | B72: 8.5 | C72: 0 | D72: 0 | E72: 720 | F72: 720 | G72: Não | H72: 1000 | I72: pendente de confirmação | J72: Sim | K72: CDB | P72: Não | Q72: IPCA | R72: Sim | S72: Spread sobre IPCA | T72: Pine | U72: pendente de confirmação | V72: Médio | W72: pendente de confirmação | X72: Secundária | Y72: Fortemente sustentado | Z72: Aplicação_Máxima, Score_Banco, Max_Usos
A73: CDB Prefixado 13,50% 24m | B73: 13.5 | C73: 0 | D73: 0 | E73: 720 | F73: 720 | G73: Não | H73: 1000 | I73: pendente de confirmação | J73: Sim | K73: CDB | P73: Não | Q73: Prefixado | R73: Sim | S73: Emissor: Genérico FGC | 13,50% a,a, | prazo 720 dias | carência 720 dias | aplicação mínima R$ 1,000,00 | FGC | T73: pendente de confirmação | U73: pendente de confirmação | V73: Médio | W73: pendente de confirmação | X73: Fora da Carteira | Y73: Pendente de confirmação | Z73: Aplicação_Máxima, Banco_Emissor, Score_Banco, Max_Usos
A74: CDB Prefixado 13,76% 12m | B74: 13.76 | C74: 0 | D74: 0 | E74: 360 | F74: 360 | G74: Não | H74: 1000 | I74: pendente de confirmação | J74: Sim | K74: CDB | P74: Não | Q74: Prefixado | R74: Sim | S74: Emissor: Genérico FGC | 13,76% a,a, | prazo 360 dias | carência 360 dias | aplicação mínima R$ 1,000,00 | FGC | T74: pendente de confirmação | U74: pendente de confirmação | V74: Médio | W74: pendente de confirmação | X74: Fora da Carteira | Y74: Pendente de confirmação | Z74: Aplicação_Máxima, Banco_Emissor, Score_Banco, Max_Usos
... A94: CDB Turbinado | B94: 103 | C94: 130 | D94: 30 | E94: 30 | F94: 0 | G94: Não | H94: 1 | I94: pendente de confirmação | J94: Não | K94: CDB | P94: Não | Q94: CDI | R94: Sim | S94: Desativado | T94: pendente de confirmação | U94: pendente de confirmação | V94: Médio | W94: pendente de confirmação | X94: Fora da Carteira | Y94: Pendente de confirmação | Z94: Aplicação_Máxima, Banco_Emissor, Score_Banco, Max_Usos
A95: CDB XP 150% | B95: 150 | C95: 0 | D95: 0 | E95: 60 | F95: 0 | G95: Não | H95: 10000 | I95: 60000 | J95: Sim | K95: CDB | P95: Não | Q95: CDI | R95: Sim | S95: Emissor: XP | 150,00% do CDI | prazo 60 dias | carência 0 dias | aplicação mínima R$ 10,000,00 | aplicação máxima R$ 60,000,00 | FGC | T95: XP | U95: pendente de confirmação | V95: Baixo | W95: pendente de confirmação | X95: Fora da Carteira | Y95: Confirmado | Z95: Score_Banco, Max_Usos
A96: CDB XP 230% | B96: 230 | C96: 0 | D96: 0 | E96: 60 | F96: 0 | G96: Não | H96: 100 | I96: 3000 | J96: Não | K96: CDB | P96: Não | Q96: CDI | R96: Sim | S96: Emissor: XP | 230,00% do CDI | prazo 60 dias | carência 0 dias | aplicação mínima R$ 100,00 | aplicação máxima R$ 3,000,00 | FGC | T96: XP | U96: pendente de confirmação | V96: Baixo | W96: pendente de confirmação | X96: Fora da Carteira | Y96: Pendente de confirmação | Z96: Score_Banco, Max_Usos
A97: Combo PicPay 100-115 | B97: 100 | C97: 115 | D97: 0 | E97: 90 | F97: 0 | G97: Não | H97: 300 | I97: pendente de confirmação | J97: Sim | K97: Combo | L97: CDB Picpay 100% | M97: CDB Picpay 115% | N97: 2 | O97: 1 | P97: Não | Q97: CDI | R97: Sim | S97: PicPay 11/04/2026 | combo atual visto no app: investir no CDB base 100% do CDI para desbloquear oferta de 115% do CDI | proporção explícita de 2:1 (cada R$ 200,00 no base libera R$ 100,00 no bônus) | saldo disponível para investir no combo estava R$ 0,00 na captura | T97: PicPay | U97: pendente de confirmação | V97: Baixo | W97: pendente de confirmação | X97: Observação/Oportunidade | Y97: Pendente de confirmação | Z97: Aplicação_Máxima, Score_Banco, Max_Usos
A98: Combo PicPay 100-120 3m | B98: 100 | C98: 120 | D98: 0 | E98: 90 | F98: 0 | G98: Não | H98: pendente de confirmação | I98: pendente de confirmação | J98: Sim | K98: Combo | L98: CDB Picpay 100% | M98: CDB Picpay 120% 3m | N98: pendente de confirmação | O98: pendente de confirmação | P98: Não | Q98: CDI | R98: Sim | S98: PicPay 11/04/2026 | existe oferta condicional de 120% do CDI associada ao CDB base de 3 meses 100% do CDI | regra exata de desbloqueio não foi exibida nesta captura; linha mantida apenas como referência do combo | T98: PicPay | U98: pendente de confirmação | V98: Baixo | W98: pendente de confirmação | X98: Observação/Oportunidade | Y98: Pendente de confirmação | Z98: Aplicação_Mínima, Aplicação_Máxima, Ratio_Base, Ratio_Bonus, Score_Banco, Max_Usos
A99: Combo PicPay 100-120 6m | B99: 100 | C99: 120 | D99: 0 | E99: 180 | F99: 0 | G99: Não | H99: pendente de confirmação | I99: pendente de confirmação | J99: Sim | K99: Combo | L99: CDB Picpay 100% | M99: CDB Picpay 120% 6m | N99: pendente de confirmação | O99: pendente de confirmação | P99: Não | Q99: CDI | R99: Sim | S99: PicPay 11/04/2026 | existe oferta condicional de 120% do CDI associada ao CDB base de 6 meses 100% do CDI | regra exata de desbloqueio não foi exibida nesta captura; linha mantida apenas como referência do combo | T99: PicPay | U99: pendente de confirmação | V99: Baixo | W99: pendente de confirmação | X99: Observação/Oportunidade | Y99: Pendente de confirmação | Z99: Aplicação_Mínima, Aplicação_Máxima, Ratio_Base, Ratio_Bonus, Score_Banco, Max_Usos
A100: Compass Credit Selection FIC de FIF RF CP LP RL | B100: 102.24 | C100: 0 | D100: 0 | E100: 1 | F100: 1 | G100: Não | H100: 500 | I100: pendente de confirmação | J100: Sim | K100: Fundo | P100: Não | Q100: CDI | R100: Não | S100: Rentab, bruta 12M 15,06%; 102,24% do CDI; Aplicação D+0; Resgate D+0 + liquidação D+1; Mov, mínima R$ 500; Saldo mínimo R$ 0; Horário 15h; Risco 4/baixo | T100: Compass | U100: pendente de confirmação | V100: Baixo | W100: pendente de confirmação | X100: Fora da Carteira | Y100: Fortemente sustentado | Z100: Aplicação_Máxima, Score_Banco, Max_Usos
A101: Compromissada ABC 80% CDI | B101: 80 | C101: 0 | D101: 0 | E101: 2 | F101: 2 | G101: Não | H101: 50000 | I101: pendente de confirmação | J101: Sim | K101: Compromissada | P101: Não | Q101: CDI | R101: Não | S101: PagBank 11/04/2026 | Banco ABC Brasil S,A, | 80,00% do CDI | vencimento 13/04/2026 | resgate no vencimento | preço unitário R$ 50,000,00 | quantidade mínima 1 | IOF isento | IR sobre rendimento | rating BRAAA pela S&P | T101: ABC | U101: pendente de confirmação | V101: Muito Baixo | W101: pendente de confirmação | X101: Fora da Carteira | Y101: Fortemente sustentado | Z101: Aplicação_Máxima, Score_Banco, Max_Usos
A102: Compromissada BancoSeguro 83% CDI | B102: 83 | C102: 0 | D102: 0 | E102: 2 | F102: 2 | G102: Não | H102: 500000 | I102: pendente de confirmação | J102: Sim | K102: Compromissada | P102: Não | Q102: CDI | R102: Não | S102: PagBank 11/04/2026 | BancoSeguro | 83,00% do CDI | vencimento 13/04/2026 | resgate no vencimento | preço unitário R$ 50,000,00 | quantidade mínima 10 | IOF isento | IR sobre rendimento | rating BRAAA pela S&P | T102: pendente de confirmação | U102: pendente de confirmação | V102: Muito Baixo | W102: pendente de confirmação | X102: Fora da Carteira | Y102: Fortemente sustentado | Z102: Aplicação_Máxima, Banco_Emissor, Score_Banco, Max_Usos
A103: Compromissada BancoSeguro 85% CDI | B103: 85 | C103: 0 | D103: 0 | E103: 2 | F103: 2 | G103: Não | H103: 1000000 | I103: pendente de confirmação | J103: Sim | K103: Compromissada | P103: Não | Q103: CDI | R103: Não | S103: PagBank 11/04/2026 | BancoSeguro | 85,00% do CDI | vencimento 13/04/2026 | resgate no vencimento | preço unitário R$ 50,000,00 | quantidade mínima 20 | IOF isento | IR sobre rendimento | rating BRAAA pela S&P | T103: pendente de confirmação | U103: pendente de confirmação | V103: Muito Baixo | W103: pendente de confirmação | X103: Fora da Carteira | Y103: Fortemente sustentado | Z103: Aplicação_Máxima, Banco_Emissor, Score_Banco, Max_Usos
A104: Compromissada BancoSeguro 88% CDI | B104: 88 | C104: 0 | D104: 0 | E104: 2 | F104: 2 | G104: Não | H104: 2500000 | I104: pendente de confirmação | J104: Sim | K104: Compromissada | P104: Não | Q104: CDI | R104: Não | S104: PagBank 11/04/2026 | BancoSeguro | 88,00% do CDI | vencimento 13/04/2026 | resgate no vencimento | preço unitário R$ 50,000,00 | quantidade mínima 50 | IOF isento | IR sobre rendimento | rating BRAAA pela S&P | T104: pendente de confirmação | U104: pendente de confirmação | V104: Muito Baixo | W104: pendente de confirmação | X104: Fora da Carteira | Y104: Fortemente sustentado | Z104: Aplicação_Máxima, Banco_Emissor, Score_Banco, Max_Usos
A105: Compromissada BancoSeguro 90% CDI | B105: 90 | C105: 0 | D105: 0 | E105: 2 | F105: 2 | G105: Não | H105: 5000000 | I105: pendente de confirmação | J105: Sim | K105: Compromissada | P105: Não | Q105: CDI | R105: Não | S105: PagBank 11/04/2026 | BancoSeguro | 90,00% do CDI | vencimento 13/04/2026 | resgate no vencimento | preço unitário R$ 50,000,00 | quantidade mínima 100 | IOF isento | IR sobre rendimento | rating BRAAA pela S&P | T105: pendente de confirmação | U105: pendente de confirmação | V105: Muito Baixo | W105: pendente de confirmação | X105: Fora da Carteira | Y105: Fortemente sustentado | Z105: Aplicação_Máxima, Banco_Emissor, Score_Banco, Max_Usos
A106: Giant Prev FIE FIC FIM | B106: 60.64 | C106: 0 | D106: 0 | E106: 1 | F106: 0 | G106: Não | H106: 100 | I106: pendente de confirmação | J106: Sim | K106: Fundo Prev | P106: Não | Q106: CDI | R106: Não | S106: Rentab, desde o início 48,20%; 60,64% do CDI; Classificação Anbima: Multimercado; Início 17/12/2019; PL R$ 82,833,925,57; Taxa adm, 1,5%; Taxa máxima 1,9%; Taxa de performance 20%; Aplicação inicial mínima R$ 100; Risco baixo 5 | T106: Giant / XP Seg | U106: pendente de confirmação | V106: Baixo | W106: pendente de confirmação | X106: Fora da Carteira | Y106: Fortemente sustentado | Z106: Aplicação_Máxima, Score_Banco, Max_Usos
A107: ICATU VANGUARDA ABSOLUTO II FI RF CP PREV | B107: 100 | C107: 0 | D107: 0 | E107: 1 | F107: 0 | G107: Não | H107: 1000 | I107: pendente de confirmação | J107: Sim | K107: Fundo Prev | P107: Não | Q107: CDI | R107: Não | S107: PicPay 11/04/2026 | Previdência | rentab, 12M 14,52% | 1M 0,24% | ano 3,09% | taxa proxy 100% CDI | prazo proxy 1 dia | T107: Icatu Vanguarda | U107: pendente de confirmação | V107: Baixo | W107: pendente de confirmação | X107: Fora da Carteira | Y107: Fortemente sustentado | Z107: Aplicação_Máxima, Score_Banco, Max_Usos
A108: ICATU VANGUARDA DINÂMICO CDI FIC DE FIF | B108: 100 | C108: 0 | D108: 0 | E108: 1 | F108: 0 | G108: Não | H108: 1000 | I108: pendente de confirmação | J108: Sim | K108: Fundo | P108: Não | Q108: CDI | R108: Não | S108: PicPay 11/04/2026 | Fundo aberto | rentab, 12M 15,39% | 1M 0,26% | ano 3,45% | taxa proxy 100% CDI | prazo proxy 1 dia | T108: Icatu Vanguarda | U108: pendente de confirmação | V108: Baixo | W108: pendente de confirmação | X108: Fora da Carteira | Y108: Fortemente sustentado | Z108: Aplicação_Máxima, Score_Banco, Max_Usos
A109: Icatu Vanguarda FI RF Plus LP - Resp, Limitada - Classe Única | B109: 100 | C109: 0 | D109: 0 | E109: 1 | F109: 1 | G109: Não | H109: 500 | I109: pendente de confirmação | J109: Sim | K109: Fundo | P109: Não | Q109: CDI | R109: Não | S109: Taxa adm, 0,28% a,a,; Cota de fechamento; Aplicação D+0; Resgate D+0 + liquidação D+1 útil; IR longo prazo; Risco baixo | T109: Icatu | U109: pendente de confirmação | V109: Baixo | W109: pendente de confirmação | X109: Fora da Carteira | Y109: Fortemente sustentado | Z109: Aplicação_Máxima, Score_Banco, Max_Usos
A110: J&F Investimentos 1 ano | B110: 115.75 | C110: 0 | D110: 0 | E110: 365 | F110: 365 | G110: Não | H110: 100 | I110: pendente de confirmação | J110: Sim | K110: Renda Fixa | P110: Não | Q110: CDI | R110: Não | S110: PicPay 11/04/2026 | CDI + 2,15% a,a, | equivalente a 115,75% do CDI | vencimento 05/05/2027 | tipo/FGC/risco não visíveis no screenshot; classificação conservadora | T110: J&F Investimentos | U110: pendente de confirmação | V110: Médio | W110: pendente de confirmação | X110: Fora da Carteira | Y110: Fortemente sustentado | Z110: Aplicação_Máxima, Score_Banco, Max_Usos
A111: J&F Investimentos 2 anos | B111: 119.16 | C111: 0 | D111: 0 | E111: 730 | F111: 730 | G111: Não | H111: 100 | I111: pendente de confirmação | J111: Sim | K111: Renda Fixa | P111: Não | Q111: CDI | R111: Não | S111: PicPay 11/04/2026 | CDI + 2,50% a,a, | equivalente a 119,16% do CDI | vencimento 05/05/2028 | tipo/FGC/risco não visíveis no screenshot; classificação conservadora | T111: J&F Investimentos | U111: pendente de confirmação | V111: Médio | W111: pendente de confirmação | X111: Fora da Carteira | Y111: Fortemente sustentado | Z111: Aplicação_Máxima, Score_Banco, Max_Usos
... A114: Kapitalo Kappa Fin FIC FIF Multim - Resp, Limitada - Classe Única | B114: 100 | C114: 0 | D114: 0 | E114: 1 | F114: 31 | G114: Não | H114: 500 | I114: pendente de confirmação | J114: Sim | K114: Fundo | P114: Não | Q114: CDI | R114: Não | S114: Taxa adm, 1,48% a,a,; Cota de fechamento; Aplicação D+0; Resgate D+30 + liquidação D+1 útil; IR longo prazo; Risco médio | T114: Kapitalo | U114: pendente de confirmação | V114: Médio | W114: pendente de confirmação | X114: Fora da Carteira | Y114: Fortemente sustentado | Z114: Aplicação_Máxima, Score_Banco, Max_Usos
A115: LCA ABC Pós-Fixado 1 ano | B115: 88.5 | C115: 0 | D115: 0 | E115: 365 | F115: 365 | G115: Sim | H115: pendente de confirmação | I115: pendente de confirmação | J115: Sim | K115: LCA | P115: Não | Q115: CDI | R115: Sim | S115: PicPay 11/04/2026 | 88,50% do CDI | vencimento 12/04/2027 | resgate no vencimento | ativo garantido pelo FGC | aplicação mínima não visível no screenshot | T115: ABC | U115: pendente de confirmação | V115: Baixo | W115: pendente de confirmação | X115: Fora da Carteira | Y115: Fortemente sustentado | Z115: Aplicação_Mínima, Aplicação_Máxima, Score_Banco, Max_Usos
A116: LCA ABC Pós-Fixado 1 ano (PagBank) | B116: 89.5 | C116: 0 | D116: 0 | E116: 365 | F116: 365 | G116: Sim | H116: 1000 | I116: pendente de confirmação | J116: Sim | K116: LCA | P116: Não | Q116: CDI | R116: Sim | S116: PagBank 11/04/2026 | Banco ABC | 89,50% do CDI | vencimento 12/04/2027 | resgate no vencimento | isento de IR | rating AAA(BRA) pela FITCH | aplicação mínima R$ 1,000,00 | T116: ABC | U116: pendente de confirmação | V116: Muito Baixo | W116: pendente de confirmação | X116: Fora da Carteira | Y116: Fortemente sustentado | Z116: Aplicação_Máxima, Score_Banco, Max_Usos
A117: LCA ABC Pós-Fixado 2 anos | B117: 89 | C117: 0 | D117: 0 | E117: 730 | F117: 730 | G117: Sim | H117: pendente de confirmação | I117: pendente de confirmação | J117: Sim | K117: LCA | P117: Não | Q117: CDI | R117: Sim | S117: PicPay 11/04/2026 | 89,00% do CDI | vencimento 10/04/2028 | resgate no vencimento | ativo garantido pelo FGC | aplicação mínima não visível no screenshot | T117: ABC | U117: pendente de confirmação | V117: Baixo | W117: pendente de confirmação | X117: Fora da Carteira | Y117: Fortemente sustentado | Z117: Aplicação_Mínima, Aplicação_Máxima, Score_Banco, Max_Usos
A118: LCA ABC Pós-Fixado 2 anos (PagBank) | B118: 90 | C118: 0 | D118: 0 | E118: 730 | F118: 730 | G118: Sim | H118: 1000 | I118: pendente de confirmação | J118: Sim | K118: LCA | P118: Não | Q118: CDI | R118: Sim | S118: PagBank 11/04/2026 | Banco ABC | 90,00% do CDI | vencimento 10/04/2028 | resgate no vencimento | isento de IR | rating AAA(BRA) pela FITCH | aplicação mínima R$ 1,000,00 | T118: ABC | U118: pendente de confirmação | V118: Muito Baixo | W118: pendente de confirmação | X118: Fora da Carteira | Y118: Fortemente sustentado | Z118: Aplicação_Máxima, Score_Banco, Max_Usos
A119: LCA ABC Prefixado 1 ano | B119: 11.94 | C119: 0 | D119: 0 | E119: 365 | F119: 365 | G119: Sim | H119: pendente de confirmação | I119: pendente de confirmação | J119: Sim | K119: LCA | P119: Não | Q119: Prefixado | R119: Sim | S119: PicPay 11/04/2026 | 11,94% a,a, | vencimento 12/04/2027 | resgate no vencimento | ativo garantido pelo FGC | aplicação mínima não visível no screenshot | T119: ABC | U119: pendente de confirmação | V119: Baixo | W119: pendente de confirmação | X119: Fora da Carteira | Y119: Fortemente sustentado | Z119: Aplicação_Mínima, Aplicação_Máxima, Score_Banco, Max_Usos
A120: LCA ABC Prefixado 2 anos | B120: 11.38 | C120: 0 | D120: 0 | E120: 730 | F120: 730 | G120: Sim | H120: pendente de confirmação | I120: pendente de confirmação | J120: Sim | K120: LCA | P120: Não | Q120: Prefixado | R120: Sim | S120: PicPay 11/04/2026 | 11,38% a,a, | vencimento 10/04/2028 | resgate no vencimento | ativo garantido pelo FGC | aplicação mínima não visível no screenshot | T120: ABC | U120: pendente de confirmação | V120: Baixo | W120: pendente de confirmação | X120: Fora da Carteira | Y120: Fortemente sustentado | Z120: Aplicação_Mínima, Aplicação_Máxima, Score_Banco, Max_Usos
A121: LCA BTG Pós-Fixado 1 ano | B121: 86 | C121: 0 | D121: 0 | E121: 365 | F121: 365 | G121: Sim | H121: pendente de confirmação | I121: pendente de confirmação | J121: Sim | K121: LCA | P121: Não | Q121: CDI | R121: Sim | S121: PicPay 11/04/2026 | 86,00% do CDI | vencimento 12/04/2027 | resgate no vencimento | ativo garantido pelo FGC | aplicação mínima não visível no screenshot | T121: BTG | U121: pendente de confirmação | V121: Baixo | W121: pendente de confirmação | X121: Fora da Carteira | Y121: Fortemente sustentado | Z121: Aplicação_Mínima, Aplicação_Máxima, Score_Banco, Max_Usos
...
